adb_grep_search/LICENSE
adb_grep_search/README.MD
adb_grep_search/__init__.py
adb_grep_search/requirements.txt
adb_grep_search/thirdparty.json
adb_grep_search-0.12.dist-info/LICENSE.rst
adb_grep_search-0.12.dist-info/METADATA
adb_grep_search-0.12.dist-info/WHEEL
adb_grep_search-0.12.dist-info/top_level.txt
adb_grep_search-0.12.dist-info/RECORD
